cb_wrapper/__init__.py
CB_ModernAPI-0.1.dist-info/LICENSE
CB_ModernAPI-0.1.dist-info/METADATA
CB_ModernAPI-0.1.dist-info/WHEEL
CB_ModernAPI-0.1.dist-info/top_level.txt
CB_ModernAPI-0.1.dist-info/RECORD
